computer_vision_datasets/__init__.py
computer_vision_datasets/module.py
computer_vision_datasets-0.2.1.dist-info/LICENSE
computer_vision_datasets-0.2.1.dist-info/METADATA
computer_vision_datasets-0.2.1.dist-info/WHEEL
computer_vision_datasets-0.2.1.dist-info/top_level.txt
computer_vision_datasets-0.2.1.dist-info/RECORD
