Metadata-Version: 2.1
Name: computer-vision-datasets
Version: 0.2.1
Summary: Easy Computer Vision Datasets
Author: Franco Marchesoni
Author-email: marchesoniacland@gmail.com
Requires-Python: >=3.6
License-File: LICENSE
Requires-Dist: tqdm
Requires-Dist: opencv-python
Requires-Dist: numpy
